storpool-7.3.0-py2.7-nspkg.pth
storpool/spapi.py
storpool/spcatch.py
storpool/spconfig.py
storpool/spdoc.py
storpool/spdocbuild.py
storpool/spjson.py
storpool/spreq.py
storpool/sptype.py
storpool/sptypes.py
storpool/sputils.py
usr/share/doc/python-storpool/apidoc.html
storpool-7.3.0.dist-info/LICENSE
storpool-7.3.0.dist-info/METADATA
storpool-7.3.0.dist-info/WHEEL
storpool-7.3.0.dist-info/entry_points.txt
storpool-7.3.0.dist-info/namespace_packages.txt
storpool-7.3.0.dist-info/top_level.txt
storpool-7.3.0.dist-info/zip-safe
storpool-7.3.0.dist-info/RECORD
