Metadata-Version: 2.1
Name: storpool
Version: 7.3.0
Summary: Bindings for the StorPool distributed storage API
Home-page: http://www.storpool.com/
Author: Peter Pentchev
Author-email: openstack-dev@storpool.com
License: Apache License 2.0
Keywords: storpool StorPool
Platform: UNKNOWN
Requires-Dist: confget (<6,>=2.2.0)
Requires-Dist: six (<2,>=1.9)
